airgap_sns/__init__.py
airgap_sns/bin/__init__.py
airgap_sns/bin/run_chat.py
airgap_sns/bin/run_client.py
airgap_sns/bin/run_host.py
airgap_sns/chat/__init__.py
airgap_sns/client/__init__.py
airgap_sns/client/client.py
airgap_sns/core/__init__.py
airgap_sns/core/audio.py
airgap_sns/core/burst.py
airgap_sns/core/crypto.py
airgap_sns/core/scheduler.py
airgap_sns/core/webhook.py
airgap_sns/email/__init__.py
airgap_sns/email/notification.py
airgap_sns/host/__init__.py
airgap_sns/host/server.py
airgap_sns/utils/__init__.py
airgap_sns-0.0.2.dist-info/METADATA
airgap_sns-0.0.2.dist-info/WHEEL
airgap_sns-0.0.2.dist-info/entry_points.txt
airgap_sns-0.0.2.dist-info/top_level.txt
airgap_sns-0.0.2.dist-info/RECORD
