Metadata-Version: 2.4
Name: airgap_sns
Version: 0.0.2
Summary: Secure Notification System with audio capabilities
Home-page: https://github.com/yourusername/airgap-sns
Author: Airgap SNS Team
Author-email: john@fimbriata.dev
Classifier: Programming Language :: Python :: 3
Classifier: License :: OSI Approved :: MIT License
Classifier: Operating System :: OS Independent
Requires-Python: >=3.8
Requires-Dist: fastapi>=0.68.0
Requires-Dist: uvicorn>=0.15.0
Requires-Dist: websockets>=10.0
Requires-Dist: pydantic>=1.8.2
Requires-Dist: cryptography>=36.0.0
Requires-Dist: aiohttp>=3.8.1
Requires-Dist: python-dotenv>=0.19.0
Requires-Dist: imaplib2>=2.57.0
Provides-Extra: audio
Requires-Dist: ggwave>=0.3.0; extra == "audio"
Requires-Dist: sounddevice>=0.4.4; extra == "audio"
Requires-Dist: numpy>=1.21.0; extra == "audio"
Provides-Extra: chat
Requires-Dist: openai>=0.27.0; extra == "chat"
Requires-Dist: httpx>=0.24.0; extra == "chat"
Provides-Extra: email
Requires-Dist: imaplib2>=2.57.0; extra == "email"
Provides-Extra: tunnel
Requires-Dist: zrok>=0.1.0; extra == "tunnel"
Provides-Extra: dev
Requires-Dist: pytest>=6.2.5; extra == "dev"
Requires-Dist: black>=21.9b0; extra == "dev"
Requires-Dist: isort>=5.9.3; extra == "dev"
Dynamic: author
Dynamic: author-email
Dynamic: classifier
Dynamic: description
Dynamic: description-content-type
Dynamic: home-page
Dynamic: provides-extra
Dynamic: requires-dist
Dynamic: requires-python
Dynamic: summary
